src/__init__.py
src/secrets_readers.py
src/secrets_writers.py
src/validation_models.py
keegcpass-0.3.0.dist-info/LICENSE.md
keegcpass-0.3.0.dist-info/METADATA
keegcpass-0.3.0.dist-info/WHEEL
keegcpass-0.3.0.dist-info/RECORD
