Metadata-Version: 2.1
Name: keegcpass
Version: 0.3.0
Summary: 
Home-page: https://github.com/andyvk85/KeeGCPass
License: MIT
Author: Andy Koch
Author-email: andyvk85@gmail.com
Requires-Python: >=3.10,<4.0
Classifier: License :: OSI Approved :: MIT License
Classifier: Programming Language :: Python :: 3
Classifier: Programming Language :: Python :: 3.10
Classifier: Programming Language :: Python :: 3.11
Classifier: Programming Language :: Python :: 3
Requires-Dist: google-cloud-secret-manager (>=2,<3)
Requires-Dist: pip-licenses (>=4,<5)
Requires-Dist: pydantic (>=1,<2)
Requires-Dist: pykeepass (>=4,<5)
Project-URL: Repository, https://github.com/andyvk85/KeeGCPass
